maniviz/__init__.py
maniviz/__main__.py
maniviz/cli.py
maniviz/maniplot.py
maniviz/models/__init__.py
maniviz/models/scara_model.py
maniviz/utils/__init__.py
maniviz/utils/logger.py
maniviz-0.0.2.dist-info/LICENSE.txt
maniviz-0.0.2.dist-info/METADATA
maniviz-0.0.2.dist-info/WHEEL
maniviz-0.0.2.dist-info/entry_points.txt
maniviz-0.0.2.dist-info/top_level.txt
maniviz-0.0.2.dist-info/RECORD
